README.md
setup.py
ascii_py/__init__.py
ascii_py/ascii_py.py
ascii_py.egg-info/PKG-INFO
ascii_py.egg-info/SOURCES.txt
ascii_py.egg-info/dependency_links.txt
ascii_py.egg-info/requires.txt
ascii_py.egg-info/top_level.txt
bin/ascii_py