Metadata-Version: 1.2
Name: ascii-py
Version: 2.0
Summary: Make ascii art
Home-page: https://www.github.com/ProfOak/Ascii_py/
Author: ProfOak
Author-email: OpenProfOak@gmail.com
License: MIT
Keywords: ascii art image fun memes
Platform: UNKNOWN
Classifier: Development Status :: 5 - Production/Stable
Classifier: Intended Audience :: End Users/Desktop
Classifier: License :: OSI Approved :: MIT License
Classifier: Operating System :: OS Independent
Classifier: Topic :: Games/Entertainment
Classifier: Topic :: Multimedia :: Graphics
Classifier: Topic :: Multimedia :: Graphics :: Editors
Classifier: Programming Language :: Python :: 3
Requires-Python: >=3.5
